itsml/__init__.py
itsml/feature_extraction/__init__.py
itsml/feature_extraction/text.py
itsml/preprocessing/text.py
itsml-0.1.2.dist-info/entry_points.txt
itsml-0.1.2.dist-info/WHEEL
itsml-0.1.2.dist-info/METADATA
itsml-0.1.2.dist-info/RECORD
