Metadata-Version: 2.1
Name: itsml
Version: 0.1.2
Summary: Tools for doing machine learning with some of my custom transformers.
Author: Alexandre Farias
Author-email: 0800alefarias@gmail.com
Requires-Python: >=3.8,<4.0
Classifier: Programming Language :: Python :: 3
Classifier: Programming Language :: Python :: 3.8
Classifier: Programming Language :: Python :: 3.9
Requires-Dist: numpy (>=1.20.1,<2.0.0)
Requires-Dist: pandas (>=1.2.3,<2.0.0)
Requires-Dist: scikit-learn (>=0.24.2,<0.25.0)
Requires-Dist: setuptools (>=57.0.0,<58.0.0)
